lawkit_python-2.5.16.dist-info/METADATA
lawkit_python-2.5.16.dist-info/WHEEL
lawkit_python.libs/libgcc_s-6d2d9dc8.so.1
lawkit_python/__init__.py
lawkit_python/lawkit_python.cpython-311-x86_64-linux-musl.so
lawkit_python-2.5.16.dist-info/RECORD
