Metadata-Version: 2.4
Name: lawkit-python
Version: 2.5.16
Classifier: Development Status :: 4 - Beta
Classifier: Intended Audience :: Developers
Classifier: Intended Audience :: Financial and Insurance Industry
Classifier: Intended Audience :: Science/Research
Classifier: License :: OSI Approved :: MIT License
Classifier: Programming Language :: Python :: 3
Classifier: Programming Language :: Python :: 3.8
Classifier: Programming Language :: Python :: 3.9
Classifier: Programming Language :: Python :: 3.10
Classifier: Programming Language :: Python :: 3.11
Classifier: Programming Language :: Python :: 3.12
Classifier: Programming Language :: Python :: 3.13
Classifier: Programming Language :: Rust
Classifier: Topic :: Scientific/Engineering :: Mathematics
Classifier: Topic :: Office/Business :: Financial
Classifier: Topic :: Software Development :: Libraries :: Python Modules
Classifier: Topic :: Security
Classifier: Topic :: Utilities
Requires-Dist: pytest>=6.0 ; extra == 'dev'
Requires-Dist: pytest-cov ; extra == 'dev'
Requires-Dist: black ; extra == 'dev'
Requires-Dist: isort ; extra == 'dev'
Requires-Dist: mypy ; extra == 'dev'
Requires-Dist: ruff ; extra == 'dev'
Provides-Extra: dev
Summary: Python bindings for lawkit - statistical law analysis toolkit for fraud detection, data quality assessment, and audit compliance. Powered by Rust for blazing fast performance.
Keywords: statistics,benford,pareto,zipf,normal,poisson,fraud-detection,audit,compliance,data-quality,forensic-accounting,statistical-analysis,pyo3,rust
Author: kako-jun
License-Expression: MIT
Requires-Python: >=3.8
Project-URL: Homepage, https://github.com/kako-jun/lawkit-python
Project-URL: Repository, https://github.com/kako-jun/lawkit-python
Project-URL: Issues, https://github.com/kako-jun/lawkit-python/issues
Project-URL: Documentation, https://github.com/kako-jun/lawkit-python#readme
